MANIFEST.in
README.md
setup.py
conan_recipe_generator/__init__.py
conan_recipe_generator/config.py
conan_recipe_generator/detect_properties.py
conan_recipe_generator/main.py
conan_recipe_generator/properties.py
conan_recipe_generator.egg-info/PKG-INFO
conan_recipe_generator.egg-info/SOURCES.txt
conan_recipe_generator.egg-info/dependency_links.txt
conan_recipe_generator.egg-info/entry_points.txt
conan_recipe_generator.egg-info/requires.txt
conan_recipe_generator.egg-info/top_level.txt
conan_recipe_generator/template/__init__.py
conan_recipe_generator/template/create.py
conan_recipe_generator/template/extensions.py
conan_recipe_generator/template/filters.py
conan_recipe_generator/template/files/config.yml
conan_recipe_generator/template/files/all/CMakeLists.txt
conan_recipe_generator/template/files/all/conandata.yml
conan_recipe_generator/template/files/all/conanfile.py
conan_recipe_generator/template/files/all/patches/0001-todo.patch
conan_recipe_generator/template/files/all/test_package/CMakeLists.txt
conan_recipe_generator/template/files/all/test_package/conanfile.py
conan_recipe_generator/template/files/all/test_package/test_package.c
conan_recipe_generator/template/files/all/test_package/test_package.cpp