Metadata-Version: 2.1
Name: conan-recipe-generator
Version: 0.0.1
Summary: Generate conan recipe from a source release
Home-page: http://github.com/madebr/conan-recipe-generator
Author: Anonymous Maarten
Author-email: anonymous.maarten@gmail.com
License: AGPLv3
Platform: UNKNOWN
Classifier: Development Status :: 1 - Planning
Classifier: Programming Language :: Python :: 3
Classifier: Programming Language :: C
Classifier: Programming Language :: C++
Classifier: License :: OSI Approved :: GNU Affero General Public License v3 or later (AGPLv3+)
Classifier: Operating System :: OS Independent
Requires-Python: >=3.7
